__init__.py
aos/CompoundSet.py
aos/FloatSet.py
aos/__init__.py
aos/constants.py
aos/operations.py
algebra_de_conjuntos-0.3.0.dist-info/METADATA
algebra_de_conjuntos-0.3.0.dist-info/WHEEL
algebra_de_conjuntos-0.3.0.dist-info/top_level.txt
algebra_de_conjuntos-0.3.0.dist-info/RECORD
